<?xml version="1.0" encoding="UTF-8" ?>
<!DOCTYPE mapper
        PUBLIC "-//mybatis.org//DTD Mapper 3.0//EN"
        "http://mybatis.org/dtd/mybatis-3-mapper.dtd">
<mapper namespace="com.codelin.dao.ChanceDao">

    <select id="findAll" resultType="Chance">
        select * from chance;
    </select>

    <insert id="addChance" parameterType="Chance">
        insert into chance (id, clientname, outline, person, phone, createperson, createtime, source, success)
        VALUES (#{id}, #{clientname}, #{outline}, #{person}, #{phone}, #{createperson}, #{createtime}, #{source}, #{success})
    </insert>

    <delete id="deleteChance" parameterType="int">
        delete from chance where id=#{id}
    </delete>

<!--    根据id查询-->
    <select id="findById" parameterType="int" resultType="Chance">
        select * from chance where id=#{id}
    </select>

<!--    更新信息-->
    <update id="update" parameterType="Chance">
        update chance set  clientname=#{clientname}, outline=#{outline}, person=#{person}, phone=#{phone}, createperson=#{createperson}, createtime=#{createtime}, source=#{source}, success=#{success} where id=#{id}
    </update>
</mapper>